t1cicd/__init__.py
t1cicd/cicd/__init__.py
t1cicd/cicd/api/README.md
t1cicd/cicd/api/__init__.py
t1cicd/cicd/api/api.py
t1cicd/cicd/api/config.py
t1cicd/cicd/api/custom_logger.py
t1cicd/cicd/api/factory.py
t1cicd/cicd/api/mock_config_override.py
t1cicd/cicd/api/run.py
t1cicd/cicd/cli/README.md
t1cicd/cicd/cli/__init__.py
t1cicd/cicd/cli/cli.py
t1cicd/cicd/cli/client.py
t1cicd/cicd/cli/commands.py
t1cicd/cicd/db/README.md
t1cicd/cicd/db/__init__.py
t1cicd/cicd/db/config.py
t1cicd/cicd/db/context/__init__.py
t1cicd/cicd/db/context/pipeline.py
t1cicd/cicd/db/db.py
t1cicd/cicd/db/migration/001_extensions.sql
t1cicd/cicd/db/migration/002_pipelines.sql
t1cicd/cicd/db/migration/003_stages.sql
t1cicd/cicd/db/migration/004_jobs.sql
t1cicd/cicd/db/migration/005_artifacts.sql
t1cicd/cicd/db/migration/__init__.py
t1cicd/cicd/db/model/__init__.py
t1cicd/cicd/db/model/artifact.py
t1cicd/cicd/db/model/job.py
t1cicd/cicd/db/model/pipeline.py
t1cicd/cicd/db/model/stage.py
t1cicd/cicd/db/repository/__init__.py
t1cicd/cicd/db/repository/artifact.py
t1cicd/cicd/db/repository/base.py
t1cicd/cicd/db/repository/job.py
t1cicd/cicd/db/repository/pipeline.py
t1cicd/cicd/db/repository/stage.py
t1cicd/cicd/db/service/__init__.py
t1cicd/cicd/db/service/pipeline.py
t1cicd/cicd/db/service/summary.py
t1cicd/cicd/db/transaction/__init__.py
t1cicd/cicd/db/transaction/base.py
t1cicd/cicd/db/transaction/pipeline.py
t1cicd/cicd/db/transform/__init__.py
t1cicd/cicd/db/transform/base.py
t1cicd/cicd/db/transform/factory.py
t1cicd/cicd/db/utils/__init__.py
t1cicd/cicd/db/utils/db_initializer.py
t1cicd/cicd/docker/README.md
t1cicd/cicd/docker/__init__.py
t1cicd/cicd/docker/docker_runner.py
t1cicd/cicd/orchestrator/README.md
t1cicd/cicd/orchestrator/__init__.py
t1cicd/cicd/orchestrator/git_handler.py
t1cicd/cicd/orchestrator/job_scheduler.py
t1cicd/cicd/orchestrator/parser/__init__.py
t1cicd/cicd/orchestrator/parser/artifact.py
t1cicd/cicd/orchestrator/parser/constants.py
t1cicd-0.1.7.dist-info/METADATA
t1cicd-0.1.7.dist-info/WHEEL
t1cicd-0.1.7.dist-info/entry_points.txt
t1cicd-0.1.7.dist-info/RECORD
