Metadata-Version: 2.1
Name: t1cicd
Version: 0.1.7
Summary: 
Author: Your Name
Author-email: you@example.com
Requires-Python: >=3.11,<4.0
Classifier: Programming Language :: Python :: 3
Classifier: Programming Language :: Python :: 3.11
Classifier: Programming Language :: Python :: 3.12
Classifier: Programming Language :: Python :: 3.13
Requires-Dist: Flask (>=3.0.3,<4.0.0)
Requires-Dist: GitPython (>=3.1.41,<4.0.0)
Requires-Dist: PyYAML (>=6.0.2,<7.0.0)
Requires-Dist: asyncpg (>=0.30.0,<0.31.0)
Requires-Dist: click (>=8.1.7,<9.0.0)
Requires-Dist: docker (>=7.1.0,<8.0.0)
Requires-Dist: flasgger (>=0.9.7.1,<0.10.0.0)
Requires-Dist: psycopg (>=3.2.3,<4.0.0)
Requires-Dist: psycopg_pool (>=3.2.3,<4.0.0)
Requires-Dist: pydantic (>=2.9.2,<3.0.0)
Requires-Dist: pytest-mock (>=3.14.0,<4.0.0)
Requires-Dist: python-dotenv (>=1.0.1,<2.0.0)
Requires-Dist: requests (>=2.32.3,<3.0.0)
Requires-Dist: rich (>=13.9.4,<14.0.0)
